p6_cdk_website_plus/__init__.py
p6_cdk_website_plus/py.typed
p6_cdk_website_plus/_jsii/__init__.py
p6_cdk_website_plus/_jsii/p6-cdk-website-plus@1.0.4.jsii.tgz
p6_cdk_website_plus-1.0.4.dist-info/LICENSE
p6_cdk_website_plus-1.0.4.dist-info/METADATA
p6_cdk_website_plus-1.0.4.dist-info/WHEEL
p6_cdk_website_plus-1.0.4.dist-info/top_level.txt
p6_cdk_website_plus-1.0.4.dist-info/RECORD
