Metadata-Version: 2.1
Name: p6-cdk-website-plus
Version: 1.0.4
Summary: R53 -> CF -> S3
Home-page: https://github.com/p6m7g8/p6-cdk-namer.git
Author: Philip M. Gollucci<pgollucci@p6m7g8.com>
License: Apache-2.0
Project-URL: Source, https://github.com/p6m7g8/p6-cdk-namer.git
Classifier: Intended Audience :: Developers
Classifier: Operating System :: OS Independent
Classifier: Programming Language :: JavaScript
Classifier: Programming Language :: Python :: 3 :: Only
Classifier: Programming Language :: Python :: 3.8
Classifier: Programming Language :: Python :: 3.9
Classifier: Programming Language :: Python :: 3.10
Classifier: Programming Language :: Python :: 3.11
Classifier: Typing :: Typed
Classifier: License :: OSI Approved
Requires-Python: ~=3.8
License-File: LICENSE
Requires-Dist: aws-cdk-lib==2.164.1
Requires-Dist: constructs<11.0.0,>=10.4.2
Requires-Dist: jsii<2.0.0,>=1.104.0
Requires-Dist: publication>=0.0.3
Requires-Dist: typeguard<4.3.0,>=2.13.3
